{"cameraMode":{"drawMode":0,"name":"Shaded","section":"Shading Mode"},"sceneLighting":true,"audioPlay":false,"sceneViewState":{"m_AlwaysRefresh":false,"showFog":true,"showSkybox":true,"showFlares":true,"showImageEffects":true,"showParticleSystems":true,"showVisualEffectGraphs":true,"m_FxEnabled":true},"in2DMode":false,"pivot":{"x":-0.0782354474067688,"y":0.2783835530281067,"z":-0.04391837120056152},"rotation":{"x":0.33921757340431216,"y":-0.4371618628501892,"z":0.1824619323015213,"w":0.8127309083938599},"size":2.2851133346557619,"orthographic":false}